{"nm":"Main Scene","ddd":0,"h":104,"w":141,"meta":{"g":"@lottiefiles/creator 1.16.0"},"layers":[{"ty":4,"nm":"Layer 1","sr":1,"st":-8,"op":150,"ip":0,"hd":false,"ddd":0,"bm":0,"hasMask":false,"ao":0,"ks":{"a":{"a":0,"k":[-899.001,-454.543,0]},"s":{"a":0,"k":[100,100]},"sk":{"a":0,"k":0},"p":{"a":1,"k":[{"o":{"x":0.167,"y":0.167},"i":{"x":0.833,"y":0.833},"s":[70.5,52],"t":0},{"o":{"x":0.167,"y":0.017},"i":{"x":0.833,"y":0.879},"s":[70.5,52],"t":9},{"o":{"x":0.167,"y":0.269},"i":{"x":0.833,"y":0.854},"s":[62.57599999999999,52],"t":10},{"o":{"x":0.167,"y":0.194},"i":{"x":0.833,"y":0.858},"s":[54.54900000000001,52],"t":11},{"o":{"x":0.167,"y":0.201},"i":{"x":0.833,"y":0.863},"s":[48.522000000000006,52],"t":12},{"o":{"x":0.167,"y":0.212},"i":{"x":0.833,"y":0.871},"s":[44.264,52],"t":13},{"o":{"x":0.167,"y":0.235},"i":{"x":0.833,"y":0.887},"s":[41.497,52],"t":14},{"o":{"x":0.167,"y":0.321},"i":{"x":0.894,"y":0},"s":[39.972,52],"t":15},{"o":{"x":0.167,"y":0.145},"i":{"x":0.833,"y":0.832},"s":[39.5,52.048],"t":16},{"o":{"x":0.167,"y":0.157},"i":{"x":0.833,"y":0.845},"s":[64.301,52],"t":22},{"o":{"x":0.167,"y":0.181},"i":{"x":0.833,"y":0.867},"s":[70.5,52],"t":23},{"o":{"x":0.167,"y":0.224},"i":{"x":0.833,"y":0.901},"s":[75.805,52],"t":24},{"o":{"x":0.167,"y":0.522},"i":{"x":0.833,"y":0.333},"s":[78.954,52],"t":25},{"o":{"x":0.167,"y":0.133},"i":{"x":0.833,"y":0.83},"s":[79.482,52],"t":26},{"o":{"x":0.167,"y":0.158},"i":{"x":0.833,"y":0.867},"s":[73.5833,52],"t":29},{"o":{"x":0.167,"y":0.224},"i":{"x":0.833,"y":0.901},"s":[67.282,52],"t":30},{"o":{"x":0.167,"y":0.522},"i":{"x":0.833,"y":0.333},"s":[67.282,52],"t":31},{"o":{"x":0.167,"y":0.133},"i":{"x":0.833,"y":0.83},"s":[65.052,52],"t":32},{"o":{"x":0.167,"y":0.158},"i":{"x":0.833,"y":0.867},"s":[70.5,52],"t":35},{"o":{"x":0.167,"y":0.224},"i":{"x":0.833,"y":0.901},"s":[72.452,52],"t":36},{"o":{"x":0.167,"y":0.522},"i":{"x":0.833,"y":0.333},"s":[73.61,52],"t":37},{"o":{"x":0.167,"y":0.133},"i":{"x":0.833,"y":0.83},"s":[73.804,52],"t":38},{"o":{"x":0.167,"y":0.158},"i":{"x":0.833,"y":0.867},"s":[70.5,52],"t":41},{"o":{"x":0.167,"y":0.224},"i":{"x":0.833,"y":0.901},"s":[69.316,52],"t":42},{"o":{"x":0.167,"y":0.523},"i":{"x":0.833,"y":0.332},"s":[68.614,52],"t":43},{"o":{"x":0.167,"y":0.133},"i":{"x":0.833,"y":0.83},"s":[68.496,52],"t":44},{"o":{"x":0.167,"y":0.158},"i":{"x":0.833,"y":0.867},"s":[70.5,52],"t":47},{"o":{"x":0.167,"y":0.224},"i":{"x":0.833,"y":0.901},"s":[71.218,52],"t":48},{"o":{"x":0.167,"y":0.521},"i":{"x":0.833,"y":0.334},"s":[71.644,52],"t":49},{"o":{"x":0.167,"y":0.133},"i":{"x":0.833,"y":0.83},"s":[71.716,52],"t":50},{"o":{"x":0.167,"y":0.158},"i":{"x":0.833,"y":0.867},"s":[70.5,52],"t":53},{"o":{"x":0.167,"y":0.224},"i":{"x":0.833,"y":0.901},"s":[70.065,52],"t":54},{"o":{"x":0.167,"y":0.525},"i":{"x":0.833,"y":0.328},"s":[69.806,52],"t":55},{"o":{"x":0.167,"y":0.133},"i":{"x":0.833,"y":0.83},"s":[69.763,52],"t":56},{"o":{"x":0.167,"y":0.158},"i":{"x":0.833,"y":0.867},"s":[70.5,52],"t":59},{"o":{"x":0.167,"y":0.224},"i":{"x":0.833,"y":0.901},"s":[70.764,52],"t":60},{"o":{"x":0.167,"y":0.519},"i":{"x":0.833,"y":0.337},"s":[70.921,52],"t":61},{"o":{"x":0.167,"y":0.133},"i":{"x":0.833,"y":0.83},"s":[70.947,52],"t":62},{"o":{"x":0.167,"y":0.158},"i":{"x":0.833,"y":0.867},"s":[70.5,52],"t":65},{"o":{"x":0.167,"y":0.224},"i":{"x":0.833,"y":0.901},"s":[70.34,52],"t":66},{"o":{"x":0.167,"y":0.528},"i":{"x":0.833,"y":0.324},"s":[70.245,52],"t":67},{"o":{"x":0.167,"y":0.133},"i":{"x":0.833,"y":0.83},"s":[70.229,52],"t":68},{"o":{"x":0.167,"y":0.158},"i":{"x":0.833,"y":0.867},"s":[70.5,52],"t":71},{"o":{"x":0.167,"y":0.224},"i":{"x":0.833,"y":0.901},"s":[70.597,52],"t":72},{"o":{"x":0.167,"y":0.53},"i":{"x":0.833,"y":0.323},"s":[70.655,52],"t":73},{"o":{"x":0.167,"y":0.133},"i":{"x":0.833,"y":0.83},"s":[70.665,52],"t":74},{"o":{"x":0.167,"y":0.158},"i":{"x":0.833,"y":0.867},"s":[70.5,52],"t":77},{"o":{"x":0.167,"y":0.224},"i":{"x":0.833,"y":0.901},"s":[70.441,52],"t":78},{"o":{"x":0.167,"y":0.519},"i":{"x":0.833,"y":0.336},"s":[70.406,52],"t":79},{"o":{"x":0.167,"y":0.133},"i":{"x":0.833,"y":0.83},"s":[70.4,52],"t":80},{"o":{"x":0.167,"y":0.158},"i":{"x":0.833,"y":0.867},"s":[70.5,52],"t":83},{"o":{"x":0.167,"y":0.224},"i":{"x":0.833,"y":0.918},"s":[70.536,52],"t":84},{"o":{"x":0.167,"y":0.347},"i":{"x":0.36,"y":1},"s":[70.557,52],"t":85},{"s":[70.548,52],"t":87}]},"r":{"a":0,"k":-450},"sa":{"a":0,"k":0},"o":{"a":0,"k":100}},"ef":[{"ty":5,"mn":"ADBE Slider Control","nm":"Position - Overshoot","ix":1,"en":1,"ef":[{"ty":0,"mn":"ADBE Slider Control-0001","nm":"Slider","ix":1,"v":{"a":0,"k":20}}]},{"ty":5,"mn":"ADBE Slider Control","nm":"Position - Bounce","ix":2,"en":1,"ef":[{"ty":0,"mn":"ADBE Slider Control-0001","nm":"Slider","ix":1,"v":{"a":0,"k":40}}]},{"ty":5,"mn":"ADBE Slider Control","nm":"Position - Friction","ix":3,"en":1,"ef":[{"ty":0,"mn":"ADBE Slider Control-0001","nm":"Slider","ix":1,"v":{"a":0,"k":40}}]}],"shapes":[{"ty":"gr","bm":0,"hd":false,"nm":"Group 1","it":[{"ty":"sh","bm":0,"hd":false,"nm":"Path 1","d":1,"ks":{"a":0,"k":{"c":true,"i":[[0,0],[0,0],[2.289,-3.539],[0,0],[1.418,0],[0.703,1.234],[0,0],[-4.375,0]],"o":[[0,0],[4.375,0],[0,0],[-0.707,1.234],[-1.422,0],[0,0],[-2.293,-3.539],[0,0]],"v":[[-944.418,-492],[-853.586,-492],[-850.043,-485.543],[-895.457,-419.082],[-898.895,-417.086],[-902.332,-419.082],[-947.957,-485.543],[-944.418,-492]]}}},{"ty":"fl","bm":0,"hd":false,"nm":"Fill 1","c":{"a":0,"k":[0.9725,0.9686,0.9647]},"r":1,"o":{"a":0,"k":100}},{"ty":"tr","a":{"a":0,"k":[0,0]},"s":{"a":0,"k":[100,100]},"sk":{"a":0,"k":0},"p":{"a":0,"k":[0,0]},"r":{"a":0,"k":0},"sa":{"a":0,"k":0},"o":{"a":0,"k":100}}]}],"ind":1}],"v":"5.7.0","fr":30,"op":150,"ip":0,"assets":[]}